[
  {
    "ContainingType": "taskmanager.Controllers.RoleController",
    "Method": "GetAll",
    "RelativePath": "api/public/Role",
    "HttpMethod": "GET",
    "IsController": true,
    "Order": 0,
    "Parameters": [],
    "ReturnTypes": []
  },
  {
    "ContainingType": "taskmanager.Controllers.RoleController",
    "Method": "Create",
    "RelativePath": "api/public/Role",
    "HttpMethod": "POST",
    "IsController": true,
    "Order": 0,
    "Parameters": [
      {
        "Name": "dto",
        "Type": "taskmanager.DTOs.Role.RoleDTO",
        "IsRequired": true
      }
    ],
    "ReturnTypes": []
  },
  {
    "ContainingType": "taskmanager.Controllers.RoleController",
    "Method": "GetById",
    "RelativePath": "api/public/Role/{id}",
    "HttpMethod": "GET",
    "IsController": true,
    "Order": 0,
    "Parameters": [
      {
        "Name": "id",
        "Type": "System.Int32",
        "IsRequired": true
      }
    ],
    "ReturnTypes": []
  },
  {
    "ContainingType": "taskmanager.Controllers.RoleController",
    "Method": "Update",
    "RelativePath": "api/public/Role/{id}",
    "HttpMethod": "PUT",
    "IsController": true,
    "Order": 0,
    "Parameters": [
      {
        "Name": "id",
        "Type": "System.Int32",
        "IsRequired": true
      },
      {
        "Name": "dto",
        "Type": "taskmanager.DTOs.Role.RoleDTO",
        "IsRequired": true
      }
    ],
    "ReturnTypes": []
  },
  {
    "ContainingType": "taskmanager.Controllers.RoleController",
    "Method": "Delete",
    "RelativePath": "api/public/Role/{id}",
    "HttpMethod": "DELETE",
    "IsController": true,
    "Order": 0,
    "Parameters": [
      {
        "Name": "id",
        "Type": "System.Int32",
        "IsRequired": true
      }
    ],
    "ReturnTypes": []
  }
]